ticketscloud.py
ticketscloud-0.6.4.dist-info/DESCRIPTION.rst
ticketscloud-0.6.4.dist-info/METADATA
ticketscloud-0.6.4.dist-info/metadata.json
ticketscloud-0.6.4.dist-info/RECORD
ticketscloud-0.6.4.dist-info/top_level.txt
ticketscloud-0.6.4.dist-info/WHEEL
